CHANGES.txt
README.txt
bootstrap.py
buildout.cfg
setup.py
src/twisted/__init__.py
src/twisted/_version.py
src/twisted/copyright.py
src/twisted/im.py
src/twisted/plugin.py
src/twisted/application/__init__.py
src/twisted/application/app.py
src/twisted/application/internet.py
src/twisted/application/reactors.py
src/twisted/application/service.py
src/twisted/application/strports.py
src/twisted/conch/__init__.py
src/twisted/conch/_version.py
src/twisted/conch/avatar.py
src/twisted/conch/checkers.py
src/twisted/conch/error.py
src/twisted/conch/interfaces.py
src/twisted/conch/ls.py
src/twisted/conch/manhole.py
src/twisted/conch/manhole_ssh.py
src/twisted/conch/manhole_tap.py
src/twisted/conch/mixin.py
src/twisted/conch/recvline.py
src/twisted/conch/stdio.py
src/twisted/conch/tap.py
src/twisted/conch/telnet.py
src/twisted/conch/ttymodes.py
src/twisted/conch/unix.py
src/twisted/conch/client/__init__.py
src/twisted/conch/client/agent.py
src/twisted/conch/client/connect.py
src/twisted/conch/client/default.py
src/twisted/conch/client/direct.py
src/twisted/conch/client/options.py
src/twisted/conch/client/unix.py
src/twisted/conch/insults/__init__.py
src/twisted/conch/insults/client.py
src/twisted/conch/insults/colors.py
src/twisted/conch/insults/helper.py
src/twisted/conch/insults/insults.py
src/twisted/conch/insults/text.py
src/twisted/conch/insults/window.py
src/twisted/conch/openssh_compat/__init__.py
src/twisted/conch/openssh_compat/factory.py
src/twisted/conch/openssh_compat/primes.py
src/twisted/conch/scripts/__init__.py
src/twisted/conch/scripts/cftp.py
src/twisted/conch/scripts/ckeygen.py
src/twisted/conch/scripts/conch.py
src/twisted/conch/scripts/tkconch.py
src/twisted/conch/ssh/__init__.py
src/twisted/conch/ssh/agent.py
src/twisted/conch/ssh/asn1.py
src/twisted/conch/ssh/channel.py
src/twisted/conch/ssh/common.py
src/twisted/conch/ssh/connection.py
src/twisted/conch/ssh/factory.py
src/twisted/conch/ssh/filetransfer.py
src/twisted/conch/ssh/forwarding.py
src/zope.app.twisted.egg-info/PKG-INFO
src/zope.app.twisted.egg-info/SOURCES.txt
src/zope.app.twisted.egg-info/dependency_links.txt
src/zope.app.twisted.egg-info/namespace_packages.txt
src/zope.app.twisted.egg-info/not-zip-safe
src/zope.app.twisted.egg-info/requires.txt
src/zope.app.twisted.egg-info/top_level.txt
